raider_reporter/__init__.py
raider_reporter/reporter.py
tests/__init__.py
tests/test_raider.py
py_raider_reporter-0.0.1.dist-info/LICENSE
py_raider_reporter-0.0.1.dist-info/METADATA
py_raider_reporter-0.0.1.dist-info/WHEEL
py_raider_reporter-0.0.1.dist-info/top_level.txt
py_raider_reporter-0.0.1.dist-info/RECORD
