Metadata-Version: 2.1
Name: py-raider-reporter
Version: 0.0.1
Summary: Raider Reporter for Python
Home-page: https://github.com/M0r13n/py-raider-reporter
Author: Leon Morten Richter
Author-email: leon.morten@gmail.com
License: MIT
Platform: UNKNOWN
Classifier: License :: OSI Approved :: MIT License
Classifier: Programming Language :: Python :: 3
Classifier: Programming Language :: Python :: 3.7
Requires-Python: >=3.6
Requires-Dist: requests
